Workbook

Sheet Dashboard
A1: Alchemist 2026 Tracker
A2: Log trades in the Trades tab; this page tells you what to do today.
A3: Mode | B3: =Settings!B20 | D3: Realised profit (gross) | E3: =SUM(Trades!$H$2:$H$1000)
A4: Capital (effective) | B4: =Settings!B14 | D4: Unrealised P/L | E4: =SUM(M12:M23)-SUM(G12:G23)
A5: Deployed | B5: =SUM(G12:G23) | D5: Gold value | E5: =Gold!H8
A6: Deployed % | B6: =Settings!B19 | D6: Gold P/L | E6: =Gold!H9
A7: Open positions | B7: =COUNTIF(F12:F23,">0") | D7: Total P/L | E7: =E3+E4+E6
A8: Actions today | B8: =COUNTIF(R12:R23,"?*")-COUNTIF(R12:R23,"Waits for trigger") | D8: Total P/L % of base capital | E8: =E7/Settings!B3
D9: Profit waiting to go into gold | E9: =Gold!H10
A10: Positions (T1 = Nifty 50 ETF, T2 = Bank Nifty partner)
A11: Track | B11: ETF | C11: Partner | D11: Buy day | E11: Last sell | F11: Units | G11: Invested | H11: Avg cost | I11: Last buy date | J11: Last buy price | K11: Cycle start | L11: Price | M11: Value | N11: P/L % | O11: Sell at | P11: Fall vs last buy | Q11: Next due | R11: ACTION | S11: Bud rank | T11: Manual price | U11: Last LUMP/SIP | V11: Bud-eligible fall
A12: T1 | B12: =Settings!B24 | C12: =B18 | D12: =Settings!A24 | E12: =_xlfn.MAXIFS(Trades!$A$2:$A$1000,Trades!$B$2:$B$1000,B12,Trades!$C$2:$C$1000,"SELL") | F12: =SUMIFS(Trades!$E$2:$E$1000,Trades!$B$2:$B$1000,B12,Trades!$C$2:$C$1000,"<>SELL")-SUMIFS(Trades!$E$2:$E$1000,Trades!$B$2:$B$1000,B12,Trades!$C$2:$C$1000,"SELL") | G12: =SUMIFS(Trades!$F$2:$F$1000,Trades!$B$2:$B$1000,B12,Trades!$C$2:$C$1000,"<>SELL",Trades!$A$2:$A$1000,">"&E12) | H12: =IF(F12>0,G12/F12,0) | I12: =IF(F12>0,_xlfn.MAXIFS(Trades!$A$2:$A$1000,Trades!$B$2:$B$1000,B12,Trades!$C$2:$C$1000,"<>SELL",Trades!$A$2:$A$1000,">"&E12),"") | J12: =IF(F12>0,IFERROR(AVERAGEIFS(Trades!$D$2:$D$1000,Trades!$B$2:$B$1000,B12,Trades!$C$2:$C$1000,"<>SELL",Trades!$A$2:$A$1000,I12),0),"") | K12: =IF(F12>0,_xlfn.MINIFS(Trades!$A$2:$A$1000,Trades!$B$2:$B$1000,B12,Trades!$C$2:$C$1000,"<>SELL",Trades!$A$2:$A$1000,">"&E12),"") | L12: =IF(ISNUMBER(T12),T12,IFERROR(GOOGLEFINANCE("NSE:"&B12),"")) | M12: =IF(F12>0,IF(ISNUMBER(L12),F12*L12,G12),0) | N12: =IF(AND(F12>0,ISNUMBER(L12)),L12/H12-1,"") | O12: =IF(F12>0,H12*(1+Settings!$B$8),"") | P12: =IF(AND(F12>0,ISNUMBER(L12)),L12/J12-1,"") | Q12: =IF(F12>0,DATE(YEAR(U12),MONTH(U12)+1,D12),IF(E12=0,IF(DAY(TODAY())<=D12,DATE(YEAR(TODAY()),MONTH(TODAY()),D12),DATE(YEAR(TODAY()),MONTH(TODAY())+1,D12)),IF(DAY(E12)<D12,DATE(YEAR(E12),MONTH(E12),D12),DATE(YEAR(E12),MONTH(E12)+1,D12)))) | R12: =IF(F12>0,IF(AND(ISNUMBER(L12),L12>=O12),"SELL ALL",IF(AND(ISNUMBER(L12),L12<=H12*(1+Settings!$B$9),F18=0),"BUY PARTNER - lump "&TEXT(Settings!$B$15,"#,##0"),IF(AND(Settings!$B$20="BUD",ISNUMBER(S12)),"BUD BUY #"&S12,IF(AND(Settings!$B$20="SHIP",TODAY()>=Q12),"SIP due - "&TEXT(Settings!$B$16,"#,##0"),"")))),IF(AND(Settings!$B$20="SHIP",TODAY()>=Q12),"LUMP due - "&TEXT(Settings!$B$15,"#,##0"),"")) | S12: =IF(ISNUMBER(V12),RANK(V12,$V$12:$V$23,1),"") | U12: =IF(F12>0,MAX(_xlfn.MAXIFS(Trades!$A$2:$A$1000,Trades!$B$2:$B$1000,B12,Trades!$C$2:$C$1000,"LUMP"),_xlfn.MAXIFS(Trades!$A$2:$A$1000,Trades!$B$2:$B$1000,B12,Trades!$C$2:$C$1000,"SIP")),"") | V12: =IF(AND(Settings!$B$20="BUD",F12>0,ISNUMBER(P12)),IF(P12<=Settings!$B$11,P12,""),"")
A13: T1 | B13: =Settings!B25 | C13: =B19 | D13: =Settings!A25 | E13: =_xlfn.MAXIFS(Trades!$A$2:$A$1000,Trades!$B$2:$B$1000,B13,Trades!$C$2:$C$1000,"SELL") | F13: =SUMIFS(Trades!$E$2:$E$1000,Trades!$B$2:$B$1000,B13,Trades!$C$2:$C$1000,"<>SELL")-SUMIFS(Trades!$E$2:$E$1000,Trades!$B$2:$B$1000,B13,Trades!$C$2:$C$1000,"SELL") | G13: =SUMIFS(Trades!$F$2:$F$1000,Trades!$B$2:$B$1000,B13,Trades!$C$2:$C$1000,"<>SELL",Trades!$A$2:$A$1000,">"&E13) | H13: =IF(F13>0,G13/F13,0) | I13: =IF(F13>0,_xlfn.MAXIFS(Trades!$A$2:$A$1000,Trades!$B$2:$B$1000,B13,Trades!$C$2:$C$1000,"<>SELL",Trades!$A$2:$A$1000,">"&E13),"") | J13: =IF(F13>0,IFERROR(AVERAGEIFS(Trades!$D$2:$D$1000,Trades!$B$2:$B$1000,B13,Trades!$C$2:$C$1000,"<>SELL",Trades!$A$2:$A$1000,I13),0),"") | K13: =IF(F13>0,_xlfn.MINIFS(Trades!$A$2:$A$1000,Trades!$B$2:$B$1000,B13,Trades!$C$2:$C$1000,"<>SELL",Trades!$A$2:$A$1000,">"&E13),"") | L13: =IF(ISNUMBER(T13),T13,IFERROR(GOOGLEFINANCE("NSE:"&B13),"")) | M13: =IF(F13>0,IF(ISNUMBER(L13),F13*L13,G13),0) | N13: =IF(AND(F13>0,ISNUMBER(L13)),L13/H13-1,"") | O13: =IF(F13>0,H13*(1+Settings!$B$8),"") | P13: =IF(AND(F13>0,ISNUMBER(L13)),L13/J13-1,"") | Q13: =IF(F13>0,DATE(YEAR(U13),MONTH(U13)+1,D13),IF(E13=0,IF(DAY(TODAY())<=D13,DATE(YEAR(TODAY()),MONTH(TODAY()),D13),DATE(YEAR(TODAY()),MONTH(TODAY())+1,D13)),IF(DAY(E13)<D13,DATE(YEAR(E13),MONTH(E13),D13),DATE(YEAR(E13),MONTH(E13)+1,D13)))) | R13: =IF(F13>0,IF(AND(ISNUMBER(L13),L13>=O13),"SELL ALL",IF(AND(ISNUMBER(L13),L13<=H13*(1+Settings!$B$9),F19=0),"BUY PARTNER - lump "&TEXT(Settings!$B$15,"#,##0"),IF(AND(Settings!$B$20="BUD",ISNUMBER(S13)),"BUD BUY #"&S13,IF(AND(Settings!$B$20="SHIP",TODAY()>=Q13),"SIP due - "&TEXT(Settings!$B$16,"#,##0"),"")))),IF(AND(Settings!$B$20="SHIP",TODAY()>=Q13),"LUMP due - "&TEXT(Settings!$B$15,"#,##0"),"")) | S13: =IF(ISNUMBER(V13),RANK(V13,$V$12:$V$23,1),"") | U13: =IF(F13>0,MAX(_xlfn.MAXIFS(Trades!$A$2:$A$1000,Trades!$B$2:$B$1000,B13,Trades!$C$2:$C$1000,"LUMP"),_xlfn.MAXIFS(Trades!$A$2:$A$1000,Trades!$B$2:$B$1000,B13,Trades!$C$2:$C$1000,"SIP")),"") | V13: =IF(AND(Settings!$B$20="BUD",F13>0,ISNUMBER(P13)),IF(P13<=Settings!$B$11,P13,""),"")
A14: T1 | B14: =Settings!B26 | C14: =B20 | D14: =Settings!A26 | E14: =_xlfn.MAXIFS(Trades!$A$2:$A$1000,Trades!$B$2:$B$1000,B14,Trades!$C$2:$C$1000,"SELL") | F14: =SUMIFS(Trades!$E$2:$E$1000,Trades!$B$2:$B$1000,B14,Trades!$C$2:$C$1000,"<>SELL")-SUMIFS(Trades!$E$2:$E$1000,Trades!$B$2:$B$1000,B14,Trades!$C$2:$C$1000,"SELL") | G14: =SUMIFS(Trades!$F$2:$F$1000,Trades!$B$2:$B$1000,B14,Trades!$C$2:$C$1000,"<>SELL",Trades!$A$2:$A$1000,">"&E14) | H14: =IF(F14>0,G14/F14,0) | I14: =IF(F14>0,_xlfn.MAXIFS(Trades!$A$2:$A$1000,Trades!$B$2:$B$1000,B14,Trades!$C$2:$C$1000,"<>SELL",Trades!$A$2:$A$1000,">"&E14),"") | J14: =IF(F14>0,IFERROR(AVERAGEIFS(Trades!$D$2:$D$1000,Trades!$B$2:$B$1000,B14,Trades!$C$2:$C$1000,"<>SELL",Trades!$A$2:$A$1000,I14),0),"") | K14: =IF(F14>0,_xlfn.MINIFS(Trades!$A$2:$A$1000,Trades!$B$2:$B$1000,B14,Trades!$C$2:$C$1000,"<>SELL",Trades!$A$2:$A$1000,">"&E14),"") | L14: =IF(ISNUMBER(T14),T14,IFERROR(GOOGLEFINANCE("NSE:"&B14),"")) | M14: =IF(F14>0,IF(ISNUMBER(L14),F14*L14,G14),0) | N14: =IF(AND(F14>0,ISNUMBER(L14)),L14/H14-1,"") | O14: =IF(F14>0,H14*(1+Settings!$B$8),"") | P14: =IF(AND(F14>0,ISNUMBER(L14)),L14/J14-1,"") | Q14: =IF(F14>0,DATE(YEAR(U14),MONTH(U14)+1,D14),IF(E14=0,IF(DAY(TODAY())<=D14,DATE(YEAR(TODAY()),MONTH(TODAY()),D14),DATE(YEAR(TODAY()),MONTH(TODAY())+1,D14)),IF(DAY(E14)<D14,DATE(YEAR(E14),MONTH(E14),D14),DATE(YEAR(E14),MONTH(E14)+1,D14)))) | R14: =IF(F14>0,IF(AND(ISNUMBER(L14),L14>=O14),"SELL ALL",IF(AND(ISNUMBER(L14),L14<=H14*(1+Settings!$B$9),F20=0),"BUY PARTNER - lump "&TEXT(Settings!$B$15,"#,##0"),IF(AND(Settings!$B$20="BUD",ISNUMBER(S14)),"BUD BUY #"&S14,IF(AND(Settings!$B$20="SHIP",TODAY()>=Q14),"SIP due - "&TEXT(Settings!$B$16,"#,##0"),"")))),IF(AND(Settings!$B$20="SHIP",TODAY()>=Q14),"LUMP due - "&TEXT(Settings!$B$15,"#,##0"),"")) | S14: =IF(ISNUMBER(V14),RANK(V14,$V$12:$V$23,1),"") | U14: =IF(F14>0,MAX(_xlfn.MAXIFS(Trades!$A$2:$A$1000,Trades!$B$2:$B$1000,B14,Trades!$C$2:$C$1000,"LUMP"),_xlfn.MAXIFS(Trades!$A$2:$A$1000,Trades!$B$2:$B$1000,B14,Trades!$C$2:$C$1000,"SIP")),"") | V14: =IF(AND(Settings!$B$20="BUD",F14>0,ISNUMBER(P14)),IF(P14<=Settings!$B$11,P14,""),"")
A15: T1 | B15: =Settings!B27 | C15: =B21 | D15: =Settings!A27 | E15: =_xlfn.MAXIFS(Trades!$A$2:$A$1000,Trades!$B$2:$B$1000,B15,Trades!$C$2:$C$1000,"SELL") | F15: =SUMIFS(Trades!$E$2:$E$1000,Trades!$B$2:$B$1000,B15,Trades!$C$2:$C$1000,"<>SELL")-SUMIFS(Trades!$E$2:$E$1000,Trades!$B$2:$B$1000,B15,Trades!$C$2:$C$1000,"SELL") | G15: =SUMIFS(Trades!$F$2:$F$1000,Trades!$B$2:$B$1000,B15,Trades!$C$2:$C$1000,"<>SELL",Trades!$A$2:$A$1000,">"&E15) | H15: =IF(F15>0,G15/F15,0) | I15: =IF(F15>0,_xlfn.MAXIFS(Trades!$A$2:$A$1000,Trades!$B$2:$B$1000,B15,Trades!$C$2:$C$1000,"<>SELL",Trades!$A$2:$A$1000,">"&E15),"") | J15: =IF(F15>0,IFERROR(AVERAGEIFS(Trades!$D$2:$D$1000,Trades!$B$2:$B$1000,B15,Trades!$C$2:$C$1000,"<>SELL",Trades!$A$2:$A$1000,I15),0),"") | K15: =IF(F15>0,_xlfn.MINIFS(Trades!$A$2:$A$1000,Trades!$B$2:$B$1000,B15,Trades!$C$2:$C$1000,"<>SELL",Trades!$A$2:$A$1000,">"&E15),"") | L15: =IF(ISNUMBER(T15),T15,IFERROR(GOOGLEFINANCE("NSE:"&B15),"")) | M15: =IF(F15>0,IF(ISNUMBER(L15),F15*L15,G15),0) | N15: =IF(AND(F15>0,ISNUMBER(L15)),L15/H15-1,"") | O15: =IF(F15>0,H15*(1+Settings!$B$8),"") | P15: =IF(AND(F15>0,ISNUMBER(L15)),L15/J15-1,"") | Q15: =IF(F15>0,DATE(YEAR(U15),MONTH(U15)+1,D15),IF(E15=0,IF(DAY(TODAY())<=D15,DATE(YEAR(TODAY()),MONTH(TODAY()),D15),DATE(YEAR(TODAY()),MONTH(TODAY())+1,D15)),IF(DAY(E15)<D15,DATE(YEAR(E15),MONTH(E15),D15),DATE(YEAR(E15),MONTH(E15)+1,D15)))) | R15: =IF(F15>0,IF(AND(ISNUMBER(L15),L15>=O15),"SELL ALL",IF(AND(ISNUMBER(L15),L15<=H15*(1+Settings!$B$9),F21=0),"BUY PARTNER - lump "&TEXT(Settings!$B$15,"#,##0"),IF(AND(Settings!$B$20="BUD",ISNUMBER(S15)),"BUD BUY #"&S15,IF(AND(Settings!$B$20="SHIP",TODAY()>=Q15),"SIP due - "&TEXT(Settings!$B$16,"#,##0"),"")))),IF(AND(Settings!$B$20="SHIP",TODAY()>=Q15),"LUMP due - "&TEXT(Settings!$B$15,"#,##0"),"")) | S15: =IF(ISNUMBER(V15),RANK(V15,$V$12:$V$23,1),"") | U15: =IF(F15>0,MAX(_xlfn.MAXIFS(Trades!$A$2:$A$1000,Trades!$B$2:$B$1000,B15,Trades!$C$2:$C$1000,"LUMP"),_xlfn.MAXIFS(Trades!$A$2:$A$1000,Trades!$B$2:$B$1000,B15,Trades!$C$2:$C$1000,"SIP")),"") | V15: =IF(AND(Settings!$B$20="BUD",F15>0,ISNUMBER(P15)),IF(P15<=Settings!$B$11,P15,""),"")
A16: T1 | B16: =Settings!B28 | C16: =B22 | D16: =Settings!A28 | E16: =_xlfn.MAXIFS(Trades!$A$2:$A$1000,Trades!$B$2:$B$1000,B16,Trades!$C$2:$C$1000,"SELL") | F16: =SUMIFS(Trades!$E$2:$E$1000,Trades!$B$2:$B$1000,B16,Trades!$C$2:$C$1000,"<>SELL")-SUMIFS(Trades!$E$2:$E$1000,Trades!$B$2:$B$1000,B16,Trades!$C$2:$C$1000,"SELL") | G16: =SUMIFS(Trades!$F$2:$F$1000,Trades!$B$2:$B$1000,B16,Trades!$C$2:$C$1000,"<>SELL",Trades!$A$2:$A$1000,">"&E16) | H16: =IF(F16>0,G16/F16,0) | I16: =IF(F16>0,_xlfn.MAXIFS(Trades!$A$2:$A$1000,Trades!$B$2:$B$1000,B16,Trades!$C$2:$C$1000,"<>SELL",Trades!$A$2:$A$1000,">"&E16),"") | J16: =IF(F16>0,IFERROR(AVERAGEIFS(Trades!$D$2:$D$1000,Trades!$B$2:$B$1000,B16,Trades!$C$2:$C$1000,"<>SELL",Trades!$A$2:$A$1000,I16),0),"") | K16: =IF(F16>0,_xlfn.MINIFS(Trades!$A$2:$A$1000,Trades!$B$2:$B$1000,B16,Trades!$C$2:$C$1000,"<>SELL",Trades!$A$2:$A$1000,">"&E16),"") | L16: =IF(ISNUMBER(T16),T16,IFERROR(GOOGLEFINANCE("NSE:"&B16),"")) | M16: =IF(F16>0,IF(ISNUMBER(L16),F16*L16,G16),0) | N16: =IF(AND(F16>0,ISNUMBER(L16)),L16/H16-1,"") | O16: =IF(F16>0,H16*(1+Settings!$B$8),"") | P16: =IF(AND(F16>0,ISNUMBER(L16)),L16/J16-1,"") | Q16: =IF(F16>0,DATE(YEAR(U16),MONTH(U16)+1,D16),IF(E16=0,IF(DAY(TODAY())<=D16,DATE(YEAR(TODAY()),MONTH(TODAY()),D16),DATE(YEAR(TODAY()),MONTH(TODAY())+1,D16)),IF(DAY(E16)<D16,DATE(YEAR(E16),MONTH(E16),D16),DATE(YEAR(E16),MONTH(E16)+1,D16)))) | R16: =IF(F16>0,IF(AND(ISNUMBER(L16),L16>=O16),"SELL ALL",IF(AND(ISNUMBER(L16),L16<=H16*(1+Settings!$B$9),F22=0),"BUY PARTNER - lump "&TEXT(Settings!$B$15,"#,##0"),IF(AND(Settings!$B$20="BUD",ISNUMBER(S16)),"BUD BUY #"&S16,IF(AND(Settings!$B$20="SHIP",TODAY()>=Q16),"SIP due - "&TEXT(Settings!$B$16,"#,##0"),"")))),IF(AND(Settings!$B$20="SHIP",TODAY()>=Q16),"LUMP due - "&TEXT(Settings!$B$15,"#,##0"),"")) | S16: =IF(ISNUMBER(V16),RANK(V16,$V$12:$V$23,1),"") | U16: =IF(F16>0,MAX(_xlfn.MAXIFS(Trades!$A$2:$A$1000,Trades!$B$2:$B$1000,B16,Trades!$C$2:$C$1000,"LUMP"),_xlfn.MAXIFS(Trades!$A$2:$A$1000,Trades!$B$2:$B$1000,B16,Trades!$C$2:$C$1000,"SIP")),"") | V16: =IF(AND(Settings!$B$20="BUD",F16>0,ISNUMBER(P16)),IF(P16<=Settings!$B$11,P16,""),"")
A17: T1 | B17: =Settings!B29 | C17: =B23 | D17: =Settings!A29 | E17: =_xlfn.MAXIFS(Trades!$A$2:$A$1000,Trades!$B$2:$B$1000,B17,Trades!$C$2:$C$1000,"SELL") | F17: =SUMIFS(Trades!$E$2:$E$1000,Trades!$B$2:$B$1000,B17,Trades!$C$2:$C$1000,"<>SELL")-SUMIFS(Trades!$E$2:$E$1000,Trades!$B$2:$B$1000,B17,Trades!$C$2:$C$1000,"SELL") | G17: =SUMIFS(Trades!$F$2:$F$1000,Trades!$B$2:$B$1000,B17,Trades!$C$2:$C$1000,"<>SELL",Trades!$A$2:$A$1000,">"&E17) | H17: =IF(F17>0,G17/F17,0) | I17: =IF(F17>0,_xlfn.MAXIFS(Trades!$A$2:$A$1000,Trades!$B$2:$B$1000,B17,Trades!$C$2:$C$1000,"<>SELL",Trades!$A$2:$A$1000,">"&E17),"") | J17: =IF(F17>0,IFERROR(AVERAGEIFS(Trades!$D$2:$D$1000,Trades!$B$2:$B$1000,B17,Trades!$C$2:$C$1000,"<>SELL",Trades!$A$2:$A$1000,I17),0),"") | K17: =IF(F17>0,_xlfn.MINIFS(Trades!$A$2:$A$1000,Trades!$B$2:$B$1000,B17,Trades!$C$2:$C$1000,"<>SELL",Trades!$A$2:$A$1000,">"&E17),"") | L17: =IF(ISNUMBER(T17),T17,IFERROR(GOOGLEFINANCE("NSE:"&B17),"")) | M17: =IF(F17>0,IF(ISNUMBER(L17),F17*L17,G17),0) | N17: =IF(AND(F17>0,ISNUMBER(L17)),L17/H17-1,"") | O17: =IF(F17>0,H17*(1+Settings!$B$8),"") | P17: =IF(AND(F17>0,ISNUMBER(L17)),L17/J17-1,"") | Q17: =IF(F17>0,DATE(YEAR(U17),MONTH(U17)+1,D17),IF(E17=0,IF(DAY(TODAY())<=D17,DATE(YEAR(TODAY()),MONTH(TODAY()),D17),DATE(YEAR(TODAY()),MONTH(TODAY())+1,D17)),IF(DAY(E17)<D17,DATE(YEAR(E17),MONTH(E17),D17),DATE(YEAR(E17),MONTH(E17)+1,D17)))) | R17: =IF(F17>0,IF(AND(ISNUMBER(L17),L17>=O17),"SELL ALL",IF(AND(ISNUMBER(L17),L17<=H17*(1+Settings!$B$9),F23=0),"BUY PARTNER - lump "&TEXT(Settings!$B$15,"#,##0"),IF(AND(Settings!$B$20="BUD",ISNUMBER(S17)),"BUD BUY #"&S17,IF(AND(Settings!$B$20="SHIP",TODAY()>=Q17),"SIP due - "&TEXT(Settings!$B$16,"#,##0"),"")))),IF(AND(Settings!$B$20="SHIP",TODAY()>=Q17),"LUMP due - "&TEXT(Settings!$B$15,"#,##0"),"")) | S17: =IF(ISNUMBER(V17),RANK(V17,$V$12:$V$23,1),"") | U17: =IF(F17>0,MAX(_xlfn.MAXIFS(Trades!$A$2:$A$1000,Trades!$B$2:$B$1000,B17,Trades!$C$2:$C$1000,"LUMP"),_xlfn.MAXIFS(Trades!$A$2:$A$1000,Trades!$B$2:$B$1000,B17,Trades!$C$2:$C$1000,"SIP")),"") | V17: =IF(AND(Settings!$B$20="BUD",F17>0,ISNUMBER(P17)),IF(P17<=Settings!$B$11,P17,""),"")
A18: T2 | B18: =Settings!C24 | C18: =B12 | D18: =IF(F18>0,DAY(K18),"") | E18: =_xlfn.MAXIFS(Trades!$A$2:$A$1000,Trades!$B$2:$B$1000,B18,Trades!$C$2:$C$1000,"SELL") | F18: =SUMIFS(Trades!$E$2:$E$1000,Trades!$B$2:$B$1000,B18,Trades!$C$2:$C$1000,"<>SELL")-SUMIFS(Trades!$E$2:$E$1000,Trades!$B$2:$B$1000,B18,Trades!$C$2:$C$1000,"SELL") | G18: =SUMIFS(Trades!$F$2:$F$1000,Trades!$B$2:$B$1000,B18,Trades!$C$2:$C$1000,"<>SELL",Trades!$A$2:$A$1000,">"&E18) | H18: =IF(F18>0,G18/F18,0) | I18: =IF(F18>0,_xlfn.MAXIFS(Trades!$A$2:$A$1000,Trades!$B$2:$B$1000,B18,Trades!$C$2:$C$1000,"<>SELL",Trades!$A$2:$A$1000,">"&E18),"") | J18: =IF(F18>0,IFERROR(AVERAGEIFS(Trades!$D$2:$D$1000,Trades!$B$2:$B$1000,B18,Trades!$C$2:$C$1000,"<>SELL",Trades!$A$2:$A$1000,I18),0),"") | K18: =IF(F18>0,_xlfn.MINIFS(Trades!$A$2:$A$1000,Trades!$B$2:$B$1000,B18,Trades!$C$2:$C$1000,"<>SELL",Trades!$A$2:$A$1000,">"&E18),"") | L18: =IF(ISNUMBER(T18),T18,IFERROR(GOOGLEFINANCE("NSE:"&B18),"")) | M18: =IF(F18>0,IF(ISNUMBER(L18),F18*L18,G18),0) | N18: =IF(AND(F18>0,ISNUMBER(L18)),L18/H18-1,"") | O18: =IF(F18>0,H18*(1+Settings!$B$8),"") | P18: =IF(AND(F18>0,ISNUMBER(L18)),L18/J18-1,"") | Q18: =IF(F18>0,DATE(YEAR(U18),MONTH(U18)+1,DAY(K18)),"") | R18: =IF(F18>0,IF(AND(ISNUMBER(L18),L18>=O18),"SELL ALL",IF(AND(Settings!$B$20="BUD",ISNUMBER(S18)),"BUD BUY #"&S18,IF(AND(Settings!$B$20="SHIP",TODAY()>=Q18),"SIP due - "&TEXT(Settings!$B$16,"#,##0"),""))),"Waits for trigger") | S18: =IF(ISNUMBER(V18),RANK(V18,$V$12:$V$23,1),"") | U18: =IF(F18>0,MAX(_xlfn.MAXIFS(Trades!$A$2:$A$1000,Trades!$B$2:$B$1000,B18,Trades!$C$2:$C$1000,"LUMP"),_xlfn.MAXIFS(Trades!$A$2:$A$1000,Trades!$B$2:$B$1000,B18,Trades!$C$2:$C$1000,"SIP")),"") | V18: =IF(AND(Settings!$B$20="BUD",F18>0,ISNUMBER(P18)),IF(P18<=Settings!$B$11,P18,""),"")
A19: T2 | B19: =Settings!C25 | C19: =B13 | D19: =IF(F19>0,DAY(K19),"") | E19: =_xlfn.MAXIFS(Trades!$A$2:$A$1000,Trades!$B$2:$B$1000,B19,Trades!$C$2:$C$1000,"SELL") | F19: =SUMIFS(Trades!$E$2:$E$1000,Trades!$B$2:$B$1000,B19,Trades!$C$2:$C$1000,"<>SELL")-SUMIFS(Trades!$E$2:$E$1000,Trades!$B$2:$B$1000,B19,Trades!$C$2:$C$1000,"SELL") | G19: =SUMIFS(Trades!$F$2:$F$1000,Trades!$B$2:$B$1000,B19,Trades!$C$2:$C$1000,"<>SELL",Trades!$A$2:$A$1000,">"&E19) | H19: =IF(F19>0,G19/F19,0) | I19: =IF(F19>0,_xlfn.MAXIFS(Trades!$A$2:$A$1000,Trades!$B$2:$B$1000,B19,Trades!$C$2:$C$1000,"<>SELL",Trades!$A$2:$A$1000,">"&E19),"") | J19: =IF(F19>0,IFERROR(AVERAGEIFS(Trades!$D$2:$D$1000,Trades!$B$2:$B$1000,B19,Trades!$C$2:$C$1000,"<>SELL",Trades!$A$2:$A$1000,I19),0),"") | K19: =IF(F19>0,_xlfn.MINIFS(Trades!$A$2:$A$1000,Trades!$B$2:$B$1000,B19,Trades!$C$2:$C$1000,"<>SELL",Trades!$A$2:$A$1000,">"&E19),"") | L19: =IF(ISNUMBER(T19),T19,IFERROR(GOOGLEFINANCE("NSE:"&B19),"")) | M19: =IF(F19>0,IF(ISNUMBER(L19),F19*L19,G19),0) | N19: =IF(AND(F19>0,ISNUMBER(L19)),L19/H19-1,"") | O19: =IF(F19>0,H19*(1+Settings!$B$8),"") | P19: =IF(AND(F19>0,ISNUMBER(L19)),L19/J19-1,"") | Q19: =IF(F19>0,DATE(YEAR(U19),MONTH(U19)+1,DAY(K19)),"") | R19: =IF(F19>0,IF(AND(ISNUMBER(L19),L19>=O19),"SELL ALL",IF(AND(Settings!$B$20="BUD",ISNUMBER(S19)),"BUD BUY #"&S19,IF(AND(Settings!$B$20="SHIP",TODAY()>=Q19),"SIP due - "&TEXT(Settings!$B$16,"#,##0"),""))),"Waits for trigger") | S19: =IF(ISNUMBER(V19),RANK(V19,$V$12:$V$23,1),"") | U19: =IF(F19>0,MAX(_xlfn.MAXIFS(Trades!$A$2:$A$1000,Trades!$B$2:$B$1000,B19,Trades!$C$2:$C$1000,"LUMP"),_xlfn.MAXIFS(Trades!$A$2:$A$1000,Trades!$B$2:$B$1000,B19,Trades!$C$2:$C$1000,"SIP")),"") | V19: =IF(AND(Settings!$B$20="BUD",F19>0,ISNUMBER(P19)),IF(P19<=Settings!$B$11,P19,""),"")
A20: T2 | B20: =Settings!C26 | C20: =B14 | D20: =IF(F20>0,DAY(K20),"") | E20: =_xlfn.MAXIFS(Trades!$A$2:$A$1000,Trades!$B$2:$B$1000,B20,Trades!$C$2:$C$1000,"SELL") | F20: =SUMIFS(Trades!$E$2:$E$1000,Trades!$B$2:$B$1000,B20,Trades!$C$2:$C$1000,"<>SELL")-SUMIFS(Trades!$E$2:$E$1000,Trades!$B$2:$B$1000,B20,Trades!$C$2:$C$1000,"SELL") | G20: =SUMIFS(Trades!$F$2:$F$1000,Trades!$B$2:$B$1000,B20,Trades!$C$2:$C$1000,"<>SELL",Trades!$A$2:$A$1000,">"&E20) | H20: =IF(F20>0,G20/F20,0) | I20: =IF(F20>0,_xlfn.MAXIFS(Trades!$A$2:$A$1000,Trades!$B$2:$B$1000,B20,Trades!$C$2:$C$1000,"<>SELL",Trades!$A$2:$A$1000,">"&E20),"") | J20: =IF(F20>0,IFERROR(AVERAGEIFS(Trades!$D$2:$D$1000,Trades!$B$2:$B$1000,B20,Trades!$C$2:$C$1000,"<>SELL",Trades!$A$2:$A$1000,I20),0),"") | K20: =IF(F20>0,_xlfn.MINIFS(Trades!$A$2:$A$1000,Trades!$B$2:$B$1000,B20,Trades!$C$2:$C$1000,"<>SELL",Trades!$A$2:$A$1000,">"&E20),"") | L20: =IF(ISNUMBER(T20),T20,IFERROR(GOOGLEFINANCE("NSE:"&B20),"")) | M20: =IF(F20>0,IF(ISNUMBER(L20),F20*L20,G20),0) | N20: =IF(AND(F20>0,ISNUMBER(L20)),L20/H20-1,"") | O20: =IF(F20>0,H20*(1+Settings!$B$8),"") | P20: =IF(AND(F20>0,ISNUMBER(L20)),L20/J20-1,"") | Q20: =IF(F20>0,DATE(YEAR(U20),MONTH(U20)+1,DAY(K20)),"") | R20: =IF(F20>0,IF(AND(ISNUMBER(L20),L20>=O20),"SELL ALL",IF(AND(Settings!$B$20="BUD",ISNUMBER(S20)),"BUD BUY #"&S20,IF(AND(Settings!$B$20="SHIP",TODAY()>=Q20),"SIP due - "&TEXT(Settings!$B$16,"#,##0"),""))),"Waits for trigger") | S20: =IF(ISNUMBER(V20),RANK(V20,$V$12:$V$23,1),"") | U20: =IF(F20>0,MAX(_xlfn.MAXIFS(Trades!$A$2:$A$1000,Trades!$B$2:$B$1000,B20,Trades!$C$2:$C$1000,"LUMP"),_xlfn.MAXIFS(Trades!$A$2:$A$1000,Trades!$B$2:$B$1000,B20,Trades!$C$2:$C$1000,"SIP")),"") | V20: =IF(AND(Settings!$B$20="BUD",F20>0,ISNUMBER(P20)),IF(P20<=Settings!$B$11,P20,""),"")
A21: T2 | B21: =Settings!C27 | C21: =B15 | D21: =IF(F21>0,DAY(K21),"") | E21: =_xlfn.MAXIFS(Trades!$A$2:$A$1000,Trades!$B$2:$B$1000,B21,Trades!$C$2:$C$1000,"SELL") | F21: =SUMIFS(Trades!$E$2:$E$1000,Trades!$B$2:$B$1000,B21,Trades!$C$2:$C$1000,"<>SELL")-SUMIFS(Trades!$E$2:$E$1000,Trades!$B$2:$B$1000,B21,Trades!$C$2:$C$1000,"SELL") | G21: =SUMIFS(Trades!$F$2:$F$1000,Trades!$B$2:$B$1000,B21,Trades!$C$2:$C$1000,"<>SELL",Trades!$A$2:$A$1000,">"&E21) | H21: =IF(F21>0,G21/F21,0) | I21: =IF(F21>0,_xlfn.MAXIFS(Trades!$A$2:$A$1000,Trades!$B$2:$B$1000,B21,Trades!$C$2:$C$1000,"<>SELL",Trades!$A$2:$A$1000,">"&E21),"") | J21: =IF(F21>0,IFERROR(AVERAGEIFS(Trades!$D$2:$D$1000,Trades!$B$2:$B$1000,B21,Trades!$C$2:$C$1000,"<>SELL",Trades!$A$2:$A$1000,I21),0),"") | K21: =IF(F21>0,_xlfn.MINIFS(Trades!$A$2:$A$1000,Trades!$B$2:$B$1000,B21,Trades!$C$2:$C$1000,"<>SELL",Trades!$A$2:$A$1000,">"&E21),"") | L21: =IF(ISNUMBER(T21),T21,IFERROR(GOOGLEFINANCE("NSE:"&B21),"")) | M21: =IF(F21>0,IF(ISNUMBER(L21),F21*L21,G21),0) | N21: =IF(AND(F21>0,ISNUMBER(L21)),L21/H21-1,"") | O21: =IF(F21>0,H21*(1+Settings!$B$8),"") | P21: =IF(AND(F21>0,ISNUMBER(L21)),L21/J21-1,"") | Q21: =IF(F21>0,DATE(YEAR(U21),MONTH(U21)+1,DAY(K21)),"") | R21: =IF(F21>0,IF(AND(ISNUMBER(L21),L21>=O21),"SELL ALL",IF(AND(Settings!$B$20="BUD",ISNUMBER(S21)),"BUD BUY #"&S21,IF(AND(Settings!$B$20="SHIP",TODAY()>=Q21),"SIP due - "&TEXT(Settings!$B$16,"#,##0"),""))),"Waits for trigger") | S21: =IF(ISNUMBER(V21),RANK(V21,$V$12:$V$23,1),"") | U21: =IF(F21>0,MAX(_xlfn.MAXIFS(Trades!$A$2:$A$1000,Trades!$B$2:$B$1000,B21,Trades!$C$2:$C$1000,"LUMP"),_xlfn.MAXIFS(Trades!$A$2:$A$1000,Trades!$B$2:$B$1000,B21,Trades!$C$2:$C$1000,"SIP")),"") | V21: =IF(AND(Settings!$B$20="BUD",F21>0,ISNUMBER(P21)),IF(P21<=Settings!$B$11,P21,""),"")
A22: T2 | B22: =Settings!C28 | C22: =B16 | D22: =IF(F22>0,DAY(K22),"") | E22: =_xlfn.MAXIFS(Trades!$A$2:$A$1000,Trades!$B$2:$B$1000,B22,Trades!$C$2:$C$1000,"SELL") | F22: =SUMIFS(Trades!$E$2:$E$1000,Trades!$B$2:$B$1000,B22,Trades!$C$2:$C$1000,"<>SELL")-SUMIFS(Trades!$E$2:$E$1000,Trades!$B$2:$B$1000,B22,Trades!$C$2:$C$1000,"SELL") | G22: =SUMIFS(Trades!$F$2:$F$1000,Trades!$B$2:$B$1000,B22,Trades!$C$2:$C$1000,"<>SELL",Trades!$A$2:$A$1000,">"&E22) | H22: =IF(F22>0,G22/F22,0) | I22: =IF(F22>0,_xlfn.MAXIFS(Trades!$A$2:$A$1000,Trades!$B$2:$B$1000,B22,Trades!$C$2:$C$1000,"<>SELL",Trades!$A$2:$A$1000,">"&E22),"") | J22: =IF(F22>0,IFERROR(AVERAGEIFS(Trades!$D$2:$D$1000,Trades!$B$2:$B$1000,B22,Trades!$C$2:$C$1000,"<>SELL",Trades!$A$2:$A$1000,I22),0),"") | K22: =IF(F22>0,_xlfn.MINIFS(Trades!$A$2:$A$1000,Trades!$B$2:$B$1000,B22,Trades!$C$2:$C$1000,"<>SELL",Trades!$A$2:$A$1000,">"&E22),"") | L22: =IF(ISNUMBER(T22),T22,IFERROR(GOOGLEFINANCE("NSE:"&B22),"")) | M22: =IF(F22>0,IF(ISNUMBER(L22),F22*L22,G22),0) | N22: =IF(AND(F22>0,ISNUMBER(L22)),L22/H22-1,"") | O22: =IF(F22>0,H22*(1+Settings!$B$8),"") | P22: =IF(AND(F22>0,ISNUMBER(L22)),L22/J22-1,"") | Q22: =IF(F22>0,DATE(YEAR(U22),MONTH(U22)+1,DAY(K22)),"") | R22: =IF(F22>0,IF(AND(ISNUMBER(L22),L22>=O22),"SELL ALL",IF(AND(Settings!$B$20="BUD",ISNUMBER(S22)),"BUD BUY #"&S22,IF(AND(Settings!$B$20="SHIP",TODAY()>=Q22),"SIP due - "&TEXT(Settings!$B$16,"#,##0"),""))),"Waits for trigger") | S22: =IF(ISNUMBER(V22),RANK(V22,$V$12:$V$23,1),"") | U22: =IF(F22>0,MAX(_xlfn.MAXIFS(Trades!$A$2:$A$1000,Trades!$B$2:$B$1000,B22,Trades!$C$2:$C$1000,"LUMP"),_xlfn.MAXIFS(Trades!$A$2:$A$1000,Trades!$B$2:$B$1000,B22,Trades!$C$2:$C$1000,"SIP")),"") | V22: =IF(AND(Settings!$B$20="BUD",F22>0,ISNUMBER(P22)),IF(P22<=Settings!$B$11,P22,""),"")
A23: T2 | B23: =Settings!C29 | C23: =B17 | D23: =IF(F23>0,DAY(K23),"") | E23: =_xlfn.MAXIFS(Trades!$A$2:$A$1000,Trades!$B$2:$B$1000,B23,Trades!$C$2:$C$1000,"SELL") | F23: =SUMIFS(Trades!$E$2:$E$1000,Trades!$B$2:$B$1000,B23,Trades!$C$2:$C$1000,"<>SELL")-SUMIFS(Trades!$E$2:$E$1000,Trades!$B$2:$B$1000,B23,Trades!$C$2:$C$1000,"SELL") | G23: =SUMIFS(Trades!$F$2:$F$1000,Trades!$B$2:$B$1000,B23,Trades!$C$2:$C$1000,"<>SELL",Trades!$A$2:$A$1000,">"&E23) | H23: =IF(F23>0,G23/F23,0) | I23: =IF(F23>0,_xlfn.MAXIFS(Trades!$A$2:$A$1000,Trades!$B$2:$B$1000,B23,Trades!$C$2:$C$1000,"<>SELL",Trades!$A$2:$A$1000,">"&E23),"") | J23: =IF(F23>0,IFERROR(AVERAGEIFS(Trades!$D$2:$D$1000,Trades!$B$2:$B$1000,B23,Trades!$C$2:$C$1000,"<>SELL",Trades!$A$2:$A$1000,I23),0),"") | K23: =IF(F23>0,_xlfn.MINIFS(Trades!$A$2:$A$1000,Trades!$B$2:$B$1000,B23,Trades!$C$2:$C$1000,"<>SELL",Trades!$A$2:$A$1000,">"&E23),"") | L23: =IF(ISNUMBER(T23),T23,IFERROR(GOOGLEFINANCE("NSE:"&B23),"")) | M23: =IF(F23>0,IF(ISNUMBER(L23),F23*L23,G23),0) | N23: =IF(AND(F23>0,ISNUMBER(L23)),L23/H23-1,"") | O23: =IF(F23>0,H23*(1+Settings!$B$8),"") | P23: =IF(AND(F23>0,ISNUMBER(L23)),L23/J23-1,"") | Q23: =IF(F23>0,DATE(YEAR(U23),MONTH(U23)+1,DAY(K23)),"") | R23: =IF(F23>0,IF(AND(ISNUMBER(L23),L23>=O23),"SELL ALL",IF(AND(Settings!$B$20="BUD",ISNUMBER(S23)),"BUD BUY #"&S23,IF(AND(Settings!$B$20="SHIP",TODAY()>=Q23),"SIP due - "&TEXT(Settings!$B$16,"#,##0"),""))),"Waits for trigger") | S23: =IF(ISNUMBER(V23),RANK(V23,$V$12:$V$23,1),"") | U23: =IF(F23>0,MAX(_xlfn.MAXIFS(Trades!$A$2:$A$1000,Trades!$B$2:$B$1000,B23,Trades!$C$2:$C$1000,"LUMP"),_xlfn.MAXIFS(Trades!$A$2:$A$1000,Trades!$B$2:$B$1000,B23,Trades!$C$2:$C$1000,"SIP")),"") | V23: =IF(AND(Settings!$B$20="BUD",F23>0,ISNUMBER(P23)),IF(P23<=Settings!$B$11,P23,""),"")

Sheet Settings
A1: Settings
A2: Yellow cells are inputs. Everything else is calculated.
A3: Total capital (base) | B3: 100000
A4: Compound profits into capital? (Yes/No) | B4: No
A5: Lump sum, % of capital | B5: 0.06
A6: SIP, % of capital | B6: 0.016
A7: Bud buy, % of SIP | B7: 0.5
A8: Sell target (gain vs average cost) | B8: 0.05
A9: Track 2 trigger (fall vs average cost) | B9: -0.05
A10: Bud mode starts above (% of capital deployed) | B10: 0.8
A11: Bud buy trigger (fall vs LAST buy price) | B11: -0.03
A12: Gold ETF code | B12: GOLDBEES
A14: Effective capital | B14: =B3+IF(B4="Yes",SUM(Trades!$H$2:$H$1000),0)
A15: Lump sum amount | B15: =B14*B5
A16: SIP amount | B16: =B14*B6
A17: Bud buy amount | B17: =B16*B7
A18: Capital deployed (open positions) | B18: =SUM(Dashboard!$G$12:$G$23)
A19: Deployed % of capital | B19: =B18/B14
A20: MODE | B20: =IF(B19>B10,"BUD","SHIP")
A22: ETF pairs
A23: Buy day | B23: Track 1 (Nifty 50) | C23: Track 2 partner (Bank Nifty) | E23: All ETF codes (for dropdowns)
A24: 1 | B24: NIFTYBEES | C24: BANKBEES | E24: =B24
A25: 5 | B25: NIFTYIETF | C25: BANKIETF | E25: =B25
A26: 10 | B26: SETFNIF50 | C26: SETFNIFBK | E26: =B26
A27: 15 | B27: NIFTY1 | C27: BANKNIFTY1 | E27: =B27
A28: 20 | B28: HDFCNIFTY | C28: HDFCNIFBAN | E28: =B28
A29: 25 | B29: NIFTYBETA | C29: BANKBETA | E29: =B29
E30: =C24
E31: =C25
E32: =C26
E33: =C27
E34: =C28
E35: =C29

Sheet Trades
A1: Date | B1: ETF code | C1: Type | D1: Price | E1: Qty | F1: Amount | G1: Brokerage + charges | H1: Realised profit (SELL rows) | I1: Notes
F2: =IF(AND(ISNUMBER(D2),ISNUMBER(E2)),D2*E2,"") | H2: =IF(C2="SELL",F2-SUMIFS($F$2:$F$1000,$B$2:$B$1000,B2,$C$2:$C$1000,"<>SELL",$A$2:$A$1000,">"&_xlfn.MAXIFS($A$2:$A$1000,$B$2:$B$1000,B2,$C$2:$C$1000,"SELL",$A$2:$A$1000,"<"&A2),$A$2:$A$1000,"<="&A2),"")
F3: =IF(AND(ISNUMBER(D3),ISNUMBER(E3)),D3*E3,"") | H3: =IF(C3="SELL",F3-SUMIFS($F$2:$F$1000,$B$2:$B$1000,B3,$C$2:$C$1000,"<>SELL",$A$2:$A$1000,">"&_xlfn.MAXIFS($A$2:$A$1000,$B$2:$B$1000,B3,$C$2:$C$1000,"SELL",$A$2:$A$1000,"<"&A3),$A$2:$A$1000,"<="&A3),"")
F4: =IF(AND(ISNUMBER(D4),ISNUMBER(E4)),D4*E4,"") | H4: =IF(C4="SELL",F4-SUMIFS($F$2:$F$1000,$B$2:$B$1000,B4,$C$2:$C$1000,"<>SELL",$A$2:$A$1000,">"&_xlfn.MAXIFS($A$2:$A$1000,$B$2:$B$1000,B4,$C$2:$C$1000,"SELL",$A$2:$A$1000,"<"&A4),$A$2:$A$1000,"<="&A4),"")
F5: =IF(AND(ISNUMBER(D5),ISNUMBER(E5)),D5*E5,"") | H5: =IF(C5="SELL",F5-SUMIFS($F$2:$F$1000,$B$2:$B$1000,B5,$C$2:$C$1000,"<>SELL",$A$2:$A$1000,">"&_xlfn.MAXIFS($A$2:$A$1000,$B$2:$B$1000,B5,$C$2:$C$1000,"SELL",$A$2:$A$1000,"<"&A5),$A$2:$A$1000,"<="&A5),"")
F6: =IF(AND(ISNUMBER(D6),ISNUMBER(E6)),D6*E6,"") | H6: =IF(C6="SELL",F6-SUMIFS($F$2:$F$1000,$B$2:$B$1000,B6,$C$2:$C$1000,"<>SELL",$A$2:$A$1000,">"&_xlfn.MAXIFS($A$2:$A$1000,$B$2:$B$1000,B6,$C$2:$C$1000,"SELL",$A$2:$A$1000,"<"&A6),$A$2:$A$1000,"<="&A6),"")
F7: =IF(AND(ISNUMBER(D7),ISNUMBER(E7)),D7*E7,"") | H7: =IF(C7="SELL",F7-SUMIFS($F$2:$F$1000,$B$2:$B$1000,B7,$C$2:$C$1000,"<>SELL",$A$2:$A$1000,">"&_xlfn.MAXIFS($A$2:$A$1000,$B$2:$B$1000,B7,$C$2:$C$1000,"SELL",$A$2:$A$1000,"<"&A7),$A$2:$A$1000,"<="&A7),"")
F8: =IF(AND(ISNUMBER(D8),ISNUMBER(E8)),D8*E8,"") | H8: =IF(C8="SELL",F8-SUMIFS($F$2:$F$1000,$B$2:$B$1000,B8,$C$2:$C$1000,"<>SELL",$A$2:$A$1000,">"&_xlfn.MAXIFS($A$2:$A$1000,$B$2:$B$1000,B8,$C$2:$C$1000,"SELL",$A$2:$A$1000,"<"&A8),$A$2:$A$1000,"<="&A8),"")
F9: =IF(AND(ISNUMBER(D9),ISNUMBER(E9)),D9*E9,"") | H9: =IF(C9="SELL",F9-SUMIFS($F$2:$F$1000,$B$2:$B$1000,B9,$C$2:$C$1000,"<>SELL",$A$2:$A$1000,">"&_xlfn.MAXIFS($A$2:$A$1000,$B$2:$B$1000,B9,$C$2:$C$1000,"SELL",$A$2:$A$1000,"<"&A9),$A$2:$A$1000,"<="&A9),"")
F10: =IF(AND(ISNUMBER(D10),ISNUMBER(E10)),D10*E10,"") | H10: =IF(C10="SELL",F10-SUMIFS($F$2:$F$1000,$B$2:$B$1000,B10,$C$2:$C$1000,"<>SELL",$A$2:$A$1000,">"&_xlfn.MAXIFS($A$2:$A$1000,$B$2:$B$1000,B10,$C$2:$C$1000,"SELL",$A$2:$A$1000,"<"&A10),$A$2:$A$1000,"<="&A10),"")
F11: =IF(AND(ISNUMBER(D11),ISNUMBER(E11)),D11*E11,"") | H11: =IF(C11="SELL",F11-SUMIFS($F$2:$F$1000,$B$2:$B$1000,B11,$C$2:$C$1000,"<>SELL",$A$2:$A$1000,">"&_xlfn.MAXIFS($A$2:$A$1000,$B$2:$B$1000,B11,$C$2:$C$1000,"SELL",$A$2:$A$1000,"<"&A11),$A$2:$A$1000,"<="&A11),"")
F12: =IF(AND(ISNUMBER(D12),ISNUMBER(E12)),D12*E12,"") | H12: =IF(C12="SELL",F12-SUMIFS($F$2:$F$1000,$B$2:$B$1000,B12,$C$2:$C$1000,"<>SELL",$A$2:$A$1000,">"&_xlfn.MAXIFS($A$2:$A$1000,$B$2:$B$1000,B12,$C$2:$C$1000,"SELL",$A$2:$A$1000,"<"&A12),$A$2:$A$1000,"<="&A12),"")
F13: =IF(AND(ISNUMBER(D13),ISNUMBER(E13)),D13*E13,"") | H13: =IF(C13="SELL",F13-SUMIFS($F$2:$F$1000,$B$2:$B$1000,B13,$C$2:$C$1000,"<>SELL",$A$2:$A$1000,">"&_xlfn.MAXIFS($A$2:$A$1000,$B$2:$B$1000,B13,$C$2:$C$1000,"SELL",$A$2:$A$1000,"<"&A13),$A$2:$A$1000,"<="&A13),"")
... F1000: =IF(AND(ISNUMBER(D1000),ISNUMBER(E1000)),D1000*E1000,"") | H1000: =IF(C1000="SELL",F1000-SUMIFS($F$2:$F$1000,$B$2:$B$1000,B1000,$C$2:$C$1000,"<>SELL",$A$2:$A$1000,">"&_xlfn.MAXIFS($A$2:$A$1000,$B$2:$B$1000,B1000,$C$2:$C$1000,"SELL",$A$2:$A$1000,"<"&A1000),$A$2:$A$1000,"<="&A1000),"")

Sheet Gold
A1: Gold accumulation
A2: Log every gold ETF purchase made with booked profits. Gold is never sold.
A4: Date | B4: Price | C4: Qty | D4: Amount | E4: Notes | G4: Units held | H4: =SUM(C5:C504)
D5: =IF(AND(ISNUMBER(B5),ISNUMBER(C5)),B5*C5,"") | G5: Invested | H5: =SUM(D5:D504)
D6: =IF(AND(ISNUMBER(B6),ISNUMBER(C6)),B6*C6,"") | G6: Manual price (optional)
D7: =IF(AND(ISNUMBER(B7),ISNUMBER(C7)),B7*C7,"") | G7: Price used | H7: =IF(ISNUMBER(H6),H6,IFERROR(GOOGLEFINANCE("NSE:"&Settings!B12),""))
D8: =IF(AND(ISNUMBER(B8),ISNUMBER(C8)),B8*C8,"") | G8: Current value | H8: =IF(ISNUMBER(H7),H4*H7,H5)
D9: =IF(AND(ISNUMBER(B9),ISNUMBER(C9)),B9*C9,"") | G9: Gold P/L | H9: =H8-H5
D10: =IF(AND(ISNUMBER(B10),ISNUMBER(C10)),B10*C10,"") | G10: Booked profit not yet put into gold | H10: =SUM(Trades!$H$2:$H$1000)-H5
D11: =IF(AND(ISNUMBER(B11),ISNUMBER(C11)),B11*C11,"")
D12: =IF(AND(ISNUMBER(B12),ISNUMBER(C12)),B12*C12,"")
D13: =IF(AND(ISNUMBER(B13),ISNUMBER(C13)),B13*C13,"")
D14: =IF(AND(ISNUMBER(B14),ISNUMBER(C14)),B14*C14,"")
D15: =IF(AND(ISNUMBER(B15),ISNUMBER(C15)),B15*C15,"")
D16: =IF(AND(ISNUMBER(B16),ISNUMBER(C16)),B16*C16,"")
D17: =IF(AND(ISNUMBER(B17),ISNUMBER(C17)),B17*C17,"")
D18: =IF(AND(ISNUMBER(B18),ISNUMBER(C18)),B18*C18,"")
D19: =IF(AND(ISNUMBER(B19),ISNUMBER(C19)),B19*C19,"")
D20: =IF(AND(ISNUMBER(B20),ISNUMBER(C20)),B20*C20,"")
D21: =IF(AND(ISNUMBER(B21),ISNUMBER(C21)),B21*C21,"")
D22: =IF(AND(ISNUMBER(B22),ISNUMBER(C22)),B22*C22,"")
... D504: =IF(AND(ISNUMBER(B504),ISNUMBER(C504)),B504*C504,"")

Sheet Guide
A1: How to use this tracker
A3: SETUP
A4: 1. Settings tab: enter your total capital (yellow). Lump sum, SIP and Bud amounts calculate themselves.
A5: 2. Confirm the six ETF pairs and buy days (yellow). Change the Gold ETF code if you use another.
A7: LOGGING (Trades tab - yellow cells only; add rows in date order)
A8: - LUMP: first buy of an ETF cycle. SIP: monthly add. BUD: a Bud-mode dip buy.
A9: - SELL: always enter the FULL quantity of that ETF. The sheet computes profit for the cycle.
A10: - Record the real broker price and quantity. Brokerage is optional.
A11: - After a SELL, buy gold with the profit and log it in the Gold tab (Dashboard shows the amount waiting).
A13: DAILY (after market, 2 minutes)
A14: - Open Dashboard. Anything in the ACTION column is something to do tomorrow/now:
A15: SELL ALL (green): price reached average cost +5%.
... A30: Not investment advice. Past backtests are not a promise.
